auth0/__init__.py
auth0/asyncify.py
auth0/authentication/__init__.py
auth0/authentication/async_token_verifier.py
auth0/authentication/back_channel_login.py
auth0/authentication/base.py
auth0/authentication/client_authentication.py
auth0/authentication/database.py
auth0/authentication/delegated.py
auth0/authentication/enterprise.py
auth0/authentication/get_token.py
auth0/authentication/passwordless.py
auth0/authentication/pushed_authorization_requests.py
auth0/authentication/revoke_token.py
auth0/authentication/social.py
auth0/authentication/token_verifier.py
auth0/authentication/users.py
auth0/exceptions.py
auth0/management/__init__.py
auth0/management/actions.py
auth0/management/async_auth0.py
auth0/management/attack_protection.py
auth0/management/auth0.py
auth0/management/blacklists.py
auth0/management/branding.py
auth0/management/client_credentials.py
auth0/management/client_grants.py
auth0/management/clients.py
auth0/management/connections.py
auth0/management/custom_domains.py
auth0/management/device_credentials.py
auth0/management/email_templates.py
auth0/management/emails.py
auth0/management/grants.py
auth0/management/guardian.py
auth0/management/hooks.py
auth0/management/jobs.py
auth0/management/log_streams.py
auth0/management/logs.py
auth0/management/network_acls.py
auth0/management/organizations.py
auth0/management/prompts.py
auth0/management/resource_servers.py
auth0/management/roles.py
auth0/management/rules.py
auth0/management/rules_configs.py
auth0/management/self_service_profiles.py
auth0/management/stats.py
auth0/management/tenants.py
auth0/management/tickets.py
auth0/management/user_blocks.py
auth0/management/users.py
auth0/management/users_by_email.py
auth0/rest.py
auth0/rest_async.py
auth0/test/__init__.py
auth0/test/authentication/__init__.py
auth0/test/authentication/test_back_channel_login.py
auth0/test/authentication/test_base.py
auth0/test/authentication/test_database.py
auth0/test/authentication/test_delegated.py
auth0_python-4.12.0.dist-info/METADATA
auth0_python-4.12.0.dist-info/WHEEL
auth0_python-4.12.0.dist-info/licenses/LICENSE
auth0_python-4.12.0.dist-info/RECORD
