Metadata-Version: 2.4
Name: auth0-python
Version: 4.12.0
Summary: 
License: MIT
License-File: LICENSE
Author: Auth0
Author-email: support@auth0.com
Requires-Python: >=3.8
Classifier: License :: OSI Approved :: MIT License
Classifier: Programming Language :: Python :: 3
Classifier: Programming Language :: Python :: 3.8
Classifier: Programming Language :: Python :: 3.9
Classifier: Programming Language :: Python :: 3.10
Classifier: Programming Language :: Python :: 3.11
Classifier: Programming Language :: Python :: 3.12
Classifier: Programming Language :: Python :: 3.13
Classifier: Programming Language :: Python :: 3.14
Requires-Dist: aiohttp (>=3.10.11)
Requires-Dist: cryptography (>=43.0.1)
Requires-Dist: pyjwt (>=2.8.0)
Requires-Dist: requests (>=2.32.3)
Requires-Dist: urllib3 (>=2.2.3)
Project-URL: Homepage, https://auth0.com
Project-URL: Repository, https://github.com/auth0/auth0-python
